grid5000/__init__.py
grid5000/__version__.py
grid5000/base.py
grid5000/cli.py
grid5000/exceptions.py
grid5000/mixins.py
grid5000/objects.py
python_grid5000-1.2.4.dist-info/LICENSE.txt
python_grid5000-1.2.4.dist-info/METADATA
python_grid5000-1.2.4.dist-info/WHEEL
python_grid5000-1.2.4.dist-info/entry_points.txt
python_grid5000-1.2.4.dist-info/top_level.txt
python_grid5000-1.2.4.dist-info/RECORD
