Metadata-Version: 2.1
Name: python-grid5000
Version: 1.2.4
Summary: UNKNOWN
Home-page: https://gitlab.inria.fr/msimonin/python-grid5000
Author: Matthieu Simonin
Author-email: matthieu.simonin@inria.fr
License: UNKNOWN
Keywords: REST,evaluation,reproducible research,Grid5000
Platform: UNKNOWN
Classifier: Development Status :: 4 - Beta
Classifier: Intended Audience :: System Administrators
Classifier: Intended Audience :: Science/Research
Classifier: License :: OSI Approved :: GNU General Public License v3 (GPLv3)
Classifier: Operating System :: POSIX :: Linux
Classifier: Programming Language :: Python
Classifier: Programming Language :: Python :: 3.6
Classifier: Programming Language :: Python :: 3.7
Classifier: Programming Language :: Python :: 3.8
Classifier: Programming Language :: Python :: 3.9
License-File: LICENSE.txt
Requires-Dist: requests (>=2.21)
Requires-Dist: pyyaml (>=5.1)
Requires-Dist: ipython
